weather_warning_summary_xethhung12/__init__.py
weather_warning_summary_xethhung12/__main__.py
weather_warning_summary_xethhung12/data_loading.py
weather_warning_summary_xethhung12-0.0.4.dist-info/METADATA
weather_warning_summary_xethhung12-0.0.4.dist-info/WHEEL
weather_warning_summary_xethhung12-0.0.4.dist-info/RECORD
